SuRFM/__init__.py
SuRFM/api/__init__.py
SuRFM/api/main.py
SuRFM/db/__init__.py
SuRFM/db/generate_data.py
SuRFM/db/save_to_csv.py
SuRFM/db/schema.py
SuRFM/db/sql_handler.py
SuRFM/logger/__init__.py
SuRFM/logger/logger.py
SuRFM/model/__init__.py
SuRFM/model/clv.py
SuRFM/model/data_processing.py
SuRFM-2.0.0.dist-info/LICENSE.txt
SuRFM-2.0.0.dist-info/METADATA
SuRFM-2.0.0.dist-info/WHEEL
SuRFM-2.0.0.dist-info/top_level.txt
SuRFM-2.0.0.dist-info/RECORD
