Metadata-Version: 2.1
Name: SuRFM
Version: 2.0.0
Summary: SuRFM is a Python package for conducting RFM (Recency, Frequency, Monetary) analysis of customers. It provides tools for segmenting customers based on their transaction behavior and identifying high-value segments.
Author: Artur Avagyan, Elen Galoyan, Hrag Sousani, Ina Karapetyan, Khoren Movsisyan
License-File: LICENSE.txt
Requires-Dist: annotated-types
Requires-Dist: anyio
Requires-Dist: exceptiongroup
Requires-Dist: Faker
Requires-Dist: fastapi
Requires-Dist: greenlet
Requires-Dist: idna
Requires-Dist: numpy
Requires-Dist: pandas
Requires-Dist: pydantic
Requires-Dist: pydantic-core
Requires-Dist: python-dateutil
Requires-Dist: pytz
Requires-Dist: six
Requires-Dist: sniffio
Requires-Dist: SQLAlchemy
Requires-Dist: starlette
Requires-Dist: typing-extensions
Requires-Dist: tzdata
Requires-Dist: appnope
Requires-Dist: asttokens
Requires-Dist: certifi
Requires-Dist: charset-normalizer
Requires-Dist: click
Requires-Dist: comm
Requires-Dist: debugpy
Requires-Dist: decorator
Requires-Dist: executing
Requires-Dist: h11
Requires-Dist: httptools
Requires-Dist: importlib-metadata
Requires-Dist: ipykernel
Requires-Dist: ipython
Requires-Dist: jedi
Requires-Dist: jupyter-client
Requires-Dist: jupyter-core
Requires-Dist: matplotlib-inline
Requires-Dist: nest-asyncio
Requires-Dist: packaging
Requires-Dist: parso
Requires-Dist: pexpect
Requires-Dist: platformdirs
Requires-Dist: prompt-toolkit
Requires-Dist: psutil
Requires-Dist: ptyprocess
Requires-Dist: pure-eval
Requires-Dist: Pygments
Requires-Dist: python-dotenv
Requires-Dist: PyYAML
Requires-Dist: pyzmq
Requires-Dist: requests
Requires-Dist: stack-data
Requires-Dist: tornado
Requires-Dist: traitlets
Requires-Dist: urllib3
Requires-Dist: uvicorn
Requires-Dist: uvloop
Requires-Dist: watchfiles
Requires-Dist: wcwidth
Requires-Dist: websockets
Requires-Dist: zipp
